pulumiverse_gandi/__init__.py
pulumiverse_gandi/_utilities.py
pulumiverse_gandi/provider.py
pulumiverse_gandi/pulumi-plugin.json
pulumiverse_gandi/py.typed
pulumiverse_gandi/config/__init__.py
pulumiverse_gandi/config/__init__.pyi
pulumiverse_gandi/config/vars.py
pulumiverse_gandi/domains/__init__.py
pulumiverse_gandi/domains/_inputs.py
pulumiverse_gandi/domains/dns_sec_key.py
pulumiverse_gandi/domains/domain.py
pulumiverse_gandi/domains/get_domain.py
pulumiverse_gandi/domains/get_glue_record.py
pulumiverse_gandi/domains/glue_record.py
pulumiverse_gandi/domains/nameservers.py
pulumiverse_gandi/domains/outputs.py
pulumiverse_gandi/email/__init__.py
pulumiverse_gandi/email/forwarding.py
pulumiverse_gandi/email/get_mailbox.py
pulumiverse_gandi/email/mailbox.py
pulumiverse_gandi/livedns/__init__.py
pulumiverse_gandi/livedns/domain.py
pulumiverse_gandi/livedns/get_domain.py
pulumiverse_gandi/livedns/get_domain_nameserver.py
pulumiverse_gandi/livedns/record.py
pulumiverse_gandi/simplehosting/__init__.py
pulumiverse_gandi/simplehosting/instance.py
pulumiverse_gandi/simplehosting/v_host.py
pulumiverse_gandi-2.3.2.dist-info/METADATA
pulumiverse_gandi-2.3.2.dist-info/WHEEL
pulumiverse_gandi-2.3.2.dist-info/top_level.txt
pulumiverse_gandi-2.3.2.dist-info/RECORD
